eon4dice/__init__.py
eon4dice/dice.py
eon4dice-1.1.1.dist-info/LICENSE
eon4dice-1.1.1.dist-info/METADATA
eon4dice-1.1.1.dist-info/WHEEL
eon4dice-1.1.1.dist-info/top_level.txt
eon4dice-1.1.1.dist-info/RECORD
