Metadata-Version: 2.1
Name: eon4dice
Version: 1.1.1
Summary: A library that handles dice rolls for the Swedish roleplaying game EON IV (https://helmgast.se/eon/).
Author-email: Oliver Glant <oliver.glant@gmail.com>
Project-URL: Homepage, https://github.com/Leopaexd/eon4dice
Project-URL: Bug Tracker, https://github.com/Leopaexd/eon4dice/issues
Classifier: Programming Language :: Python :: 3
Classifier: License :: OSI Approved :: MIT License
Classifier: Operating System :: OS Independent
Requires-Python: >=3.1
License-File: LICENSE
